quikarit/__init__.py
quikarit/core.py
quikarit-0.2.0.dist-info/licenses/LICENSE.txt
quikarit-0.2.0.dist-info/METADATA
quikarit-0.2.0.dist-info/WHEEL
quikarit-0.2.0.dist-info/top_level.txt
quikarit-0.2.0.dist-info/RECORD
