Metadata-Version: 2.4
Name: quikarit
Version: 0.2.0
Summary: Quikarit adds some QoL functions to python, including sorting algorithms and matrix functions.
Author-email: Lucas da Costa <lucasdacostacampos8@example.com>
Maintainer-email: Lucas da Costa <lucasdacostacampos8@example.com>
License: MIT
Project-URL: Documentation, https://quikarit.rf.gd
Project-URL: Changelogs, https://quikarit.rf.gd/changelogs.html
Project-URL: Repository, https://github.com/Lucas-doubleC/quikarit
Keywords: quikarit,math,QoL,Quality of Life
Classifier: Programming Language :: Python :: 3
Requires-Python: >=3.8
License-File: LICENSE.txt
Dynamic: license-file
